{
	"backtrace" : 0,
	"backtraceGraph" : 
	{
		"commands" : [],
		"files" : 
		[
			"CMakeLists.txt"
		],
		"nodes" : 
		[
			{
				"file" : 0
			}
		]
	},
	"id" : "Notatnik_autogen_timestamp_deps::@6890427a1f51a3e7e1df",
	"isGeneratorProvided" : true,
	"name" : "Notatnik_autogen_timestamp_deps",
	"paths" : 
	{
		"build" : ".",
		"source" : "."
	},
	"sourceGroups" : 
	[
		{
			"name" : "",
			"sourceIndexes" : 
			[
				0
			]
		},
		{
			"name" : "CMake Rules",
			"sourceIndexes" : 
			[
				1
			]
		}
	],
	"sources" : 
	[
		{
			"backtrace" : 0,
			"isGenerated" : true,
			"path" : "C:/Users/MM/Documents/GitHub/PK4_Gr2/build-Notatnik-Desktop_Qt_6_0_2_MSVC2019_64bit-Debug/CMakeFiles/Notatnik_autogen_timestamp_deps",
			"sourceGroupIndex" : 0
		},
		{
			"backtrace" : 0,
			"isGenerated" : true,
			"path" : "C:/Users/MM/Documents/GitHub/PK4_Gr2/build-Notatnik-Desktop_Qt_6_0_2_MSVC2019_64bit-Debug/CMakeFiles/Notatnik_autogen_timestamp_deps.rule",
			"sourceGroupIndex" : 1
		}
	],
	"type" : "UTILITY"
}
